webmesh/__init__.py
webmesh/message_protocols.py
webmesh/message_serializers.py
webmesh/utils.py
webmesh/webmesh_client.py
webmesh/webmesh_component.py
webmesh/webmesh_server.py
webmesh-0.1.2.dist-info/METADATA
webmesh-0.1.2.dist-info/WHEEL
webmesh-0.1.2.dist-info/RECORD
