Metadata-Version: 2.1
Name: webmesh
Version: 0.1.2
Summary: "Connects microservices through a mesh of websockets"
Home-page: UNKNOWN
Author: "Charles Smith"
Author-email: "binarskugga@gmail.com"
License: "Copyright"
Platform: UNKNOWN
